{
  "@context": "https://schema.org",
  "@type": "Product",
  "@id": "amazon-pet-B0B42PQPZD",
  "name": "Aswadh Guinea Pig Accessories Hamster House Toy Soft Plush Sleeping Bed Mice Pink",
  "description": "Description:Mini hamster nest, thick pumpkin pet nest, suitable for small pets such as guinea pigs, hedgehogs, squirrels, guinea pigs, etc.High-quality crystal velvet fabric, thick sponge, thick and warm, high elasticity and not easy to collapse, soft and not easy to deformThe top handle design makes it easy to carry around. A variety of colors are available, there is always a suitable petSurrounding design creates a closed space, locks the temperature, and makes pets feel safe and relaxedThe bottom is non-slip design, wear-resistant and durable, easy to clean, prevent the breeding of dust and",
  "image": "https://m.media-amazon.com/images/I/41Ns88UY0NL._SS522_.jpg",
  "sku": "amazon-pet-B0B42PQPZD",
  "brand": {
    "@type": "Brand",
    "name": "Generic"
  },
  "offers": {
    "@type": "Offer",
    "price": 1.755,
    "priceCurrency": "INR",
    "availability": "https://schema.org/OutOfStock"
  },
  "keywords": [
    "small-pet-toy",
    "pet-supplies",
    "small-animals",
    "houses-habitats",
    "beds"
  ]
}