{
  "source": "petsmart",
  "url": "https://www.petsmart.com/cat/food-and-treats/food-toppers/fancy-feast-broths-adult-cat-wet-food---1.55-oz.-limited-ingredients-grain-free-27693.html",
  "breadcrumb": "cat > food-and-treats > food-toppers > fancy-feast-broths-adult-cat-wet-food---1.55-oz.-limited-ingredients-grain-free-27693.html",
  "bucket": "cat-wet-food",
  "gtin13": "0050000291052",
  "images": {
    "large": "https://s7d2.scene7.com/is/image/PetSmart/5231496?$sclp-prd-main_large$",
    "medium": "https://s7d2.scene7.com/is/image/PetSmart/5231496?$sclp-prd-main_medium$",
    "small": "https://s7d2.scene7.com/is/image/PetSmart/5231496?$sclp-prd-main_small$"
  }
}