{
  "@context": "https://schema.org",
  "@type": "Product",
  "@id": "amazon-pet-B09TDWFJ45",
  "name": "KUTKUT Pack of 2 Striped Dress for Small Dog Girl Puppy Clothes Female Princess Tutu Frock Skirt Summer Shirt for Shihtzu, Pug, Poodle Cat Pet Apparel Outfits (Size: 2XL, Chest: 55cm)",
  "description": "Please measure your dog size before you purchase according to the size chart below Product Description: L: Bust 45cm/17.72in Back length 35cm/13.78in. XL: Bust 50cm/19.69in Back length 40cm/15.75in. 2XL: Bust 55cm/21.65in Back length 45cm/17.72in.",
  "image": "https://m.media-amazon.com/images/I/51Ye4usFK6L._SS522_.jpg",
  "sku": "amazon-pet-B09TDWFJ45",
  "brand": {
    "@type": "Brand",
    "name": "Visit the KUTKUT Store"
  },
  "offers": {
    "@type": "Offer",
    "price": 1.099,
    "priceCurrency": "INR",
    "availability": "https://schema.org/InStock"
  },
  "keywords": [
    "dog-accessory",
    "pet-supplies",
    "dogs",
    "apparel-accessories",
    "dresses"
  ]
}