{
  "@context": "https://schema.org",
  "@type": "Product",
  "@id": "amazon-pet-B09KRSM8DD",
  "name": "Ubersweet® Imported 3BD7 Pet Dog Cat Flashing Ball Creative Interactive Moving Funny",
  "description": "Ubersweet Imported 3BD7 Pet Dog Cat Flashing Ball Creative Interactive Moving Funny. New & Imported Item. Delivers within 3 to 5 weeks",
  "image": "https://m.media-amazon.com/images/I/41tYj-SurNL._SS522_.jpg",
  "sku": "amazon-pet-B09KRSM8DD",
  "brand": {
    "@type": "Brand",
    "name": "ubersweet"
  },
  "offers": {
    "@type": "Offer",
    "price": 1.587,
    "priceCurrency": "INR",
    "availability": "https://schema.org/OutOfStock"
  },
  "keywords": [
    "dog-toy",
    "pet-supplies",
    "cats",
    "toys",
    "interactive-toys"
  ]
}